stellars_jupyterlab_extensions/__init__.py
stellars_jupyterlab_extensions-1.0.19.dist-info/METADATA
stellars_jupyterlab_extensions-1.0.19.dist-info/WHEEL
stellars_jupyterlab_extensions-1.0.19.dist-info/RECORD
