Metadata-Version: 2.4
Name: stellars_jupyterlab_extensions
Version: 1.0.19
Summary: Metapackage aggregating all Stellars JupyterLab extensions
Project-URL: Homepage, https://github.com/stellarshenson
Project-URL: Repository, https://github.com/stellarshenson
Author-email: Konrad Jelen <konrad.jelen+github@gmail.com>
License: MIT
Keywords: extensions,jupyter,jupyterlab
Classifier: Framework :: Jupyter
Classifier: Framework :: Jupyter :: JupyterLab
Classifier: Framework :: Jupyter :: JupyterLab :: 4
Classifier: License :: OSI Approved :: MIT License
Classifier: Programming Language :: Python
Classifier: Programming Language :: Python :: 3
Classifier: Programming Language :: Python :: 3.10
Classifier: Programming Language :: Python :: 3.11
Classifier: Programming Language :: Python :: 3.12
Requires-Python: >=3.10
Requires-Dist: jupyterlab-colourful-tab-extension
Requires-Dist: jupyterlab-doc-reader-extension
Requires-Dist: jupyterlab-drawio-render-extension
Requires-Dist: jupyterlab-export-markdown-extension
Requires-Dist: jupyterlab-file-browser-sorting-extension
Requires-Dist: jupyterlab-fit-image-size-extension
Requires-Dist: jupyterlab-fold-all-code-extension
Requires-Dist: jupyterlab-github-markdown-alerts-extension
Requires-Dist: jupyterlab-makefile-file-type-extension
Requires-Dist: jupyterlab-markdown-insert-content-extension
Requires-Dist: jupyterlab-mmd-to-png-extension
Requires-Dist: jupyterlab-nb-venv-kernels-ui-extension
Requires-Dist: jupyterlab-notifications-extension
Requires-Dist: jupyterlab-refresh-view-extension
Requires-Dist: jupyterlab-tabular-data-viewer-extension
Requires-Dist: jupyterlab-terminal-show-in-file-browser-extension
Requires-Dist: jupyterlab-terraform-file-type-extension
Requires-Dist: jupyterlab-trash-mgmt-extension
Requires-Dist: jupyterlab-vscode-icons-extension
Requires-Dist: jupyterlab-zip-extension
